[
  {
    "author": "AutoLovepon",
    "created_utc": 1707684380.0,
    "downs": 0,
    "discussion_type": null,
    "hide_score": false,
    "id": "1aoi22i",
    "num_comments": 1,
    "saved": false,
    "score": 2,
    "subreddit_id": "t5_2qh22",
    "title": "Yami Shibai 12 \u2022 Theatre of Darkness: Yamishibai 12 - Episode 5 discussion",
    "total_awards_received": 0,
    "url": "https://www.reddit.com/r/anime/comments/1aoi22i/yami_shibai_12_theatre_of_darkness_yamishibai_12/",
    "ups": 2,
    "upvote_ratio": 0.75,
    "view_count": null,
    "visited": false,
    "data_pull_date": {
      "timestamp": 1707715844.41289,
      "date": "2024-02-12 05:30:44"
    },
    "show_name": "Yami Shibai 12 \u2022 Theatre of Darkness: Yamishibai 12",
    "season_number": 1,
    "episode_number": "5"
  },
  {
    "author": "AutoLovepon",
    "created_utc": 1707677181.0,
    "downs": 0,
    "discussion_type": null,
    "hide_score": false,
    "id": "1aof76j",
    "num_comments": 15,
    "saved": false,
    "score": 85,
    "subreddit_id": "t5_2qh22",
    "title": "Kyuujitsu no Warumono-san \u2022 Mr. Villain's Day Off - Episode 6 discussion",
    "total_awards_received": 0,
    "url": "https://www.reddit.com/r/anime/comments/1aof76j/kyuujitsu_no_warumonosan_mr_villains_day_off/",
    "ups": 85,
    "upvote_ratio": 0.89,
    "view_count": null,
    "visited": false,
    "data_pull_date": {
      "timestamp": 1707715844.41289,
      "date": "2024-02-12 05:30:44"
    },
    "show_name": "Kyuujitsu no Warumono-san \u2022 Mr. Villain's Day Off",
    "season_number": 1,
    "episode_number": "6"
  },
  {
    "author": "AutoLovepon",
    "created_utc": 1707673407.0,
    "downs": 0,
    "discussion_type": null,
    "hide_score": false,
    "id": "1aodopx",
    "num_comments": 105,
    "saved": false,
    "score": 363,
    "subreddit_id": "t5_2qh22",
    "title": "Ninja Kamui - Episode 1 discussion",
    "total_awards_received": 0,
    "url": "https://www.reddit.com/r/anime/comments/1aodopx/ninja_kamui_episode_1_discussion/",
    "ups": 363,
    "upvote_ratio": 0.96,
    "view_count": null,
    "visited": false,
    "data_pull_date": {
      "timestamp": 1707715844.41289,
      "date": "2024-02-12 05:30:44"
    },
    "show_name": "Ninja Kamui",
    "season_number": 1,
    "episode_number": "1"
  },
  {
    "author": "AutoLovepon",
    "created_utc": 1707669075.0,
    "downs": 0,
    "discussion_type": null,
    "hide_score": false,
    "id": "1aobyxi",
    "num_comments": 10,
    "saved": false,
    "score": 49,
    "subreddit_id": "t5_2qh22",
    "title": "Hikari no Ou Season 2 \u2022 The Fire Hunter Season 2 - Episode 15 discussion",
    "total_awards_received": 0,
    "url": "https://www.reddit.com/r/anime/comments/1aobyxi/hikari_no_ou_season_2_the_fire_hunter_season_2/",
    "ups": 49,
    "upvote_ratio": 0.85,
    "view_count": null,
    "visited": false,
    "data_pull_date": {
      "timestamp": 1707715844.41289,
      "date": "2024-02-12 05:30:44"
    },
    "show_name": "Hikari no Ou Season 2 \u2022 The Fire Hunter Season 2",
    "season_number": "2",
    "episode_number": "15"
  },
  {
    "author": "AutoLovepon",
    "created_utc": 1707667445.0,
    "downs": 0,
    "discussion_type": null,
    "hide_score": false,
    "id": "1aobb9w",
    "num_comments": 17,
    "saved": false,
    "score": 31,
    "subreddit_id": "t5_2qh22",
    "title": "Meiji Gekken: 1874 - Episode 5 discussion",
    "total_awards_received": 0,
    "url": "https://www.reddit.com/r/anime/comments/1aobb9w/meiji_gekken_1874_episode_5_discussion/",
    "ups": 31,
    "upvote_ratio": 0.85,
    "view_count": null,
    "visited": false,
    "data_pull_date": {
      "timestamp": 1707715844.41289,
      "date": "2024-02-12 05:30:44"
    },
    "show_name": "Meiji Gekken: 1874",
    "season_number": 1,
    "episode_number": "5"
  },
  {
    "author": "AutoLovepon",
    "created_utc": 1707665477.0,
    "downs": 0,
    "discussion_type": null,
    "hide_score": false,
    "id": "1aoajw1",
    "num_comments": 74,
    "saved": false,
    "score": 259,
    "subreddit_id": "t5_2qh22",
    "title": "Shin no Nakama ja Nai to Yuusha no Party wo Oidasareta node, Henkyou de Slow Life suru Koto ni Shimashita Season 2 \u2022 Banished from the Hero's Party, I Decided to Live a Quiet Life in the Countryside Season 2 - Episode 6 discussion",
    "total_awards_received": 0,
    "url": "https://www.reddit.com/r/anime/comments/1aoajw1/shin_no_nakama_ja_nai_to_yuusha_no_party_wo/",
    "ups": 259,
    "upvote_ratio": 0.94,
    "view_count": null,
    "visited": false,
    "data_pull_date": {
      "timestamp": 1707715844.41289,
      "date": "2024-02-12 05:30:44"
    },
    "show_name": "Shin no Nakama ja Nai to Yuusha no Party wo Oidasareta node, Henkyou de Slow Life suru Koto ni Shimashita Season 2 \u2022 Banished from the Hero's Party, I Decided to Live a Quiet Life in the Countryside Season 2",
    "season_number": "2",
    "episode_number": "6"
  },
  {
    "author": "AutoLovepon",
    "created_utc": 1707664580.0,
    "downs": 0,
    "discussion_type": null,
    "hide_score": false,
    "id": "1aoa7qv",
    "num_comments": 211,
    "saved": false,
    "score": 684,
    "subreddit_id": "t5_2qh22",
    "title": "Loop 7-kaime no Akuyaku Reijou wa, Moto Tekikoku de Jiyuu Kimama na Hanayome Seikatsu wo Mankitsu suru \u2022 7th Time Loop: The Villainess Enjoys a Carefree Life Married to Her Worst Enemy! - Episode 6 discussion",
    "total_awards_received": 0,
    "url": "https://www.reddit.com/r/anime/comments/1aoa7qv/loop_7kaime_no_akuyaku_reijou_wa_moto_tekikoku_de/",
    "ups": 684,
    "upvote_ratio": 0.98,
    "view_count": null,
    "visited": false,
    "data_pull_date": {
      "timestamp": 1707715844.41289,
      "date": "2024-02-12 05:30:44"
    },
    "show_name": "Loop 7-kaime no Akuyaku Reijou wa, Moto Tekikoku de Jiyuu Kimama na Hanayome Seikatsu wo Mankitsu suru \u2022 7th Time Loop: The Villainess Enjoys a Carefree Life Married to Her Worst Enemy!",
    "season_number": 1,
    "episode_number": "6"
  },
  {
    "author": "AutoLovepon",
    "created_utc": 1707663677.0,
    "downs": 0,
    "discussion_type": null,
    "hide_score": false,
    "id": "1ao9veu",
    "num_comments": 46,
    "saved": false,
    "score": 122,
    "subreddit_id": "t5_2qh22",
    "title": "Isekai de Mofumofu Nadenade suru Tame ni Ganbattemasu. \u2022 Fluffy Paradise - Episode 7 discussion",
    "total_awards_received": 0,
    "url": "https://www.reddit.com/r/anime/comments/1ao9veu/isekai_de_mofumofu_nadenade_suru_tame_ni/",
    "ups": 122,
    "upvote_ratio": 0.91,
    "view_count": null,
    "visited": false,
    "data_pull_date": {
      "timestamp": 1707715844.41289,
      "date": "2024-02-12 05:30:44"
    },
    "show_name": "Isekai de Mofumofu Nadenade suru Tame ni Ganbattemasu. \u2022 Fluffy Paradise",
    "season_number": 1,
    "episode_number": "7"
  },
  {
    "author": "AutoLovepon",
    "created_utc": 1707647662.0,
    "downs": 0,
    "discussion_type": null,
    "hide_score": false,
    "id": "1ao54ax",
    "num_comments": 463,
    "saved": false,
    "score": 1823,
    "subreddit_id": "t5_2qh22",
    "title": "Shangri-La Frontier - Episode 18 discussion",
    "total_awards_received": 0,
    "url": "https://www.reddit.com/r/anime/comments/1ao54ax/shangrila_frontier_episode_18_discussion/",
    "ups": 1823,
    "upvote_ratio": 0.96,
    "view_count": null,
    "visited": false,
    "data_pull_date": {
      "timestamp": 1707715844.41289,
      "date": "2024-02-12 05:30:44"
    },
    "show_name": "Shangri-La Frontier",
    "season_number": 1,
    "episode_number": "18"
  },
  {
    "author": "AutoLovepon",
    "created_utc": 1707642611.0,
    "downs": 0,
    "discussion_type": null,
    "hide_score": false,
    "id": "1ao3x76",
    "num_comments": 2,
    "saved": false,
    "score": 15,
    "subreddit_id": "t5_2qh22",
    "title": "Captain Tsubasa Season 2: Junior Youth-hen \u2022 'Captain Tsubasa Jr. Youth Arc - Episode 19 discussion",
    "total_awards_received": 0,
    "url": "https://www.reddit.com/r/anime/comments/1ao3x76/captain_tsubasa_season_2_junior_youthhen_captain/",
    "ups": 15,
    "upvote_ratio": 0.86,
    "view_count": null,
    "visited": false,
    "data_pull_date": {
      "timestamp": 1707715844.41289,
      "date": "2024-02-12 05:30:44"
    },
    "show_name": "Captain Tsubasa Season 2: Junior Youth-hen \u2022 'Captain Tsubasa Jr. Youth Arc",
    "season_number": "2",
    "episode_number": "19"
  },
  {
    "author": "AutoLovepon",
    "created_utc": 1707617061.0,
    "downs": 0,
    "discussion_type": null,
    "hide_score": false,
    "id": "1anwsm7",
    "num_comments": 46,
    "saved": false,
    "score": 246,
    "subreddit_id": "t5_2qh22",
    "title": "One Piece - Episode 1093 discussion",
    "total_awards_received": 0,
    "url": "https://www.reddit.com/r/anime/comments/1anwsm7/one_piece_episode_1093_discussion/",
    "ups": 246,
    "upvote_ratio": 0.91,
    "view_count": null,
    "visited": false,
    "data_pull_date": {
      "timestamp": 1707715844.41289,
      "date": "2024-02-12 05:30:44"
    },
    "show_name": "One Piece",
    "season_number": 1,
    "episode_number": "1093"
  },
  {
    "author": "AutoLovepon",
    "created_utc": 1707615075.0,
    "downs": 0,
    "discussion_type": null,
    "hide_score": false,
    "id": "1anw5gi",
    "num_comments": 56,
    "saved": false,
    "score": 57,
    "subreddit_id": "t5_2qh22",
    "title": "Wonderful Precure! \u2022 Wonderful Pretty Cure! - Episode 2 discussion",
    "total_awards_received": 0,
    "url": "https://www.reddit.com/r/anime/comments/1anw5gi/wonderful_precure_wonderful_pretty_cure_episode_2/",
    "ups": 57,
    "upvote_ratio": 0.88,
    "view_count": null,
    "visited": false,
    "data_pull_date": {
      "timestamp": 1707715844.41289,
      "date": "2024-02-12 05:30:44"
    },
    "show_name": "Wonderful Precure! \u2022 Wonderful Pretty Cure!",
    "season_number": 1,
    "episode_number": "2"
  },
  {
    "author": "AutoLovepon",
    "created_utc": 1707593473.0,
    "downs": 0,
    "discussion_type": null,
    "hide_score": false,
    "id": "1ano926",
    "num_comments": 15,
    "saved": false,
    "score": 131,
    "subreddit_id": "t5_2qh22",
    "title": "Kingdom Season 5 - Episode 5 discussion",
    "total_awards_received": 0,
    "url": "https://www.reddit.com/r/anime/comments/1ano926/kingdom_season_5_episode_5_discussion/",
    "ups": 131,
    "upvote_ratio": 0.96,
    "view_count": null,
    "visited": false,
    "data_pull_date": {
      "timestamp": 1707715844.41289,
      "date": "2024-02-12 05:30:44"
    },
    "show_name": "Kingdom Season 5",
    "season_number": "5",
    "episode_number": "5"
  },
  {
    "author": "AutoLovepon",
    "created_utc": 1707591849.0,
    "downs": 0,
    "discussion_type": null,
    "hide_score": false,
    "id": "1annn65",
    "num_comments": 58,
    "saved": false,
    "score": 126,
    "subreddit_id": "t5_2qh22",
    "title": "Saikyou Tank no Meikyuu Kouryaku: Tairyoku 9999 no Rare Skill-mochi Tank, Yuusha Party wo Tsuihou sareru \u2022 The Strongest Tank's Labyrinth Raids: A Tank with a Rare 9999 Resistance Skill Got Kicked from the Hero's Party - Episode 6 discussion",
    "total_awards_received": 0,
    "url": "https://www.reddit.com/r/anime/comments/1annn65/saikyou_tank_no_meikyuu_kouryaku_tairyoku_9999_no/",
    "ups": 126,
    "upvote_ratio": 0.87,
    "view_count": null,
    "visited": false,
    "data_pull_date": {
      "timestamp": 1707715844.41289,
      "date": "2024-02-12 05:30:44"
    },
    "show_name": "Saikyou Tank no Meikyuu Kouryaku: Tairyoku 9999 no Rare Skill-mochi Tank, Yuusha Party wo Tsuihou sareru \u2022 The Strongest Tank's Labyrinth Raids: A Tank with a Rare 9999 Resistance Skill Got Kicked from the Hero's Party",
    "season_number": 1,
    "episode_number": "6"
  },
  {
    "author": "AutoLovepon",
    "created_utc": 1707590782.0,
    "downs": 0,
    "discussion_type": null,
    "hide_score": false,
    "id": "1ann8v5",
    "num_comments": 533,
    "saved": false,
    "score": 2785,
    "subreddit_id": "t5_2qh22",
    "title": "Kusuriya no Hitorigoto \u2022 The Apothecary Diaries - Episode 18 discussion",
    "total_awards_received": 0,
    "url": "https://www.reddit.com/r/anime/comments/1ann8v5/kusuriya_no_hitorigoto_the_apothecary_diaries/",
    "ups": 2785,
    "upvote_ratio": 0.98,
    "view_count": null,
    "visited": false,
    "data_pull_date": {
      "timestamp": 1707715844.41289,
      "date": "2024-02-12 05:30:44"
    },
    "show_name": "Kusuriya no Hitorigoto \u2022 The Apothecary Diaries",
    "season_number": 1,
    "episode_number": "18"
  },
  {
    "author": "AutoLovepon",
    "created_utc": 1707588263.0,
    "downs": 0,
    "discussion_type": null,
    "hide_score": false,
    "id": "1anmajj",
    "num_comments": 523,
    "saved": false,
    "score": 2071,
    "subreddit_id": "t5_2qh22",
    "title": "Boku no Kokoro no Yabai Yatsu Season 2 \u2022 The Dangers in My Heart Season 2 - Episode 6 discussion",
    "total_awards_received": 0,
    "url": "https://www.reddit.com/r/anime/comments/1anmajj/boku_no_kokoro_no_yabai_yatsu_season_2_the/",
    "ups": 2071,
    "upvote_ratio": 0.96,
    "view_count": null,
    "visited": false,
    "data_pull_date": {
      "timestamp": 1707715844.41289,
      "date": "2024-02-12 05:30:44"
    },
    "show_name": "Boku no Kokoro no Yabai Yatsu Season 2 \u2022 The Dangers in My Heart Season 2",
    "season_number": "2",
    "episode_number": "6"
  },
  {
    "author": "AutoLovepon",
    "created_utc": 1707586274.0,
    "downs": 0,
    "discussion_type": null,
    "hide_score": false,
    "id": "1anlj9n",
    "num_comments": 958,
    "saved": false,
    "score": 3808,
    "subreddit_id": "t5_2qh22",
    "title": "Ore dake Level Up na Ken \u2022 Solo Leveling - Episode 6 discussion",
    "total_awards_received": 0,
    "url": "https://www.reddit.com/r/anime/comments/1anlj9n/ore_dake_level_up_na_ken_solo_leveling_episode_6/",
    "ups": 3808,
    "upvote_ratio": 0.9,
    "view_count": null,
    "visited": false,
    "data_pull_date": {
      "timestamp": 1707715844.41289,
      "date": "2024-02-12 05:30:44"
    },
    "show_name": "Ore dake Level Up na Ken \u2022 Solo Leveling",
    "season_number": 1,
    "episode_number": "6"
  },
  {
    "author": "AutoLovepon",
    "created_utc": 1707585021.0,
    "downs": 0,
    "discussion_type": null,
    "hide_score": false,
    "id": "1anl1ie",
    "num_comments": 38,
    "saved": false,
    "score": 177,
    "subreddit_id": "t5_2qh22",
    "title": "Ao no Exorcist Shimane Illuminati-hen \u2022 Blue Exorcist -Shimane Illuminati Saga- - Episode 6 discussion",
    "total_awards_received": 0,
    "url": "https://www.reddit.com/r/anime/comments/1anl1ie/ao_no_exorcist_shimane_illuminatihen_blue/",
    "ups": 177,
    "upvote_ratio": 0.93,
    "view_count": null,
    "visited": false,
    "data_pull_date": {
      "timestamp": 1707715844.41289,
      "date": "2024-02-12 05:30:44"
    },
    "show_name": "Ao no Exorcist Shimane Illuminati-hen \u2022 Blue Exorcist -Shimane Illuminati Saga-",
    "season_number": 1,
    "episode_number": "6"
  },
  {
    "author": "AutoLovepon",
    "created_utc": 1707582677.0,
    "downs": 0,
    "discussion_type": null,
    "hide_score": false,
    "id": "1ank6dg",
    "num_comments": 135,
    "saved": false,
    "score": 237,
    "subreddit_id": "t5_2qh22",
    "title": "Bucchigiri?! - Episode 5 discussion",
    "total_awards_received": 0,
    "url": "https://www.reddit.com/r/anime/comments/1ank6dg/bucchigiri_episode_5_discussion/",
    "ups": 237,
    "upvote_ratio": 0.92,
    "view_count": null,
    "visited": false,
    "data_pull_date": {
      "timestamp": 1707715844.41289,
      "date": "2024-02-12 05:30:44"
    },
    "show_name": "Bucchigiri?!",
    "season_number": 1,
    "episode_number": "5"
  },
  {
    "author": "AutoLovepon",
    "created_utc": 1707580886.0,
    "downs": 0,
    "discussion_type": null,
    "hide_score": false,
    "id": "1anjilf",
    "num_comments": 294,
    "saved": false,
    "score": 580,
    "subreddit_id": "t5_2qh22",
    "title": "Ragna Crimson - Episode 17 discussion",
    "total_awards_received": 0,
    "url": "https://www.reddit.com/r/anime/comments/1anjilf/ragna_crimson_episode_17_discussion/",
    "ups": 580,
    "upvote_ratio": 0.96,
    "view_count": null,
    "visited": false,
    "data_pull_date": {
      "timestamp": 1707715844.41289,
      "date": "2024-02-12 05:30:44"
    },
    "show_name": "Ragna Crimson",
    "season_number": 1,
    "episode_number": "17"
  },
  {
    "author": "AutoLovepon",
    "created_utc": 1707577460.0,
    "downs": 0,
    "discussion_type": null,
    "hide_score": false,
    "id": "1ani9r8",
    "num_comments": 146,
    "saved": false,
    "score": 739,
    "subreddit_id": "t5_2qh22",
    "title": "Yubisaki to Renren \u2022 A Sign of Affection - Episode 6 discussion",
    "total_awards_received": 0,
    "url": "https://www.reddit.com/r/anime/comments/1ani9r8/yubisaki_to_renren_a_sign_of_affection_episode_6/",
    "ups": 739,
    "upvote_ratio": 0.96,
    "view_count": null,
    "visited": false,
    "data_pull_date": {
      "timestamp": 1707715844.41289,
      "date": "2024-02-12 05:30:44"
    },
    "show_name": "Yubisaki to Renren \u2022 A Sign of Affection",
    "season_number": 1,
    "episode_number": "6"
  },
  {
    "author": "AutoLovepon",
    "created_utc": 1707570261.0,
    "downs": 0,
    "discussion_type": null,
    "hide_score": false,
    "id": "1anfvtf",
    "num_comments": 90,
    "saved": false,
    "score": 252,
    "subreddit_id": "t5_2qh22",
    "title": "Kekkon Yubiwa Monogatari \u2022 Tales of Wedding Rings - Episode 6 discussion",
    "total_awards_received": 0,
    "url": "https://www.reddit.com/r/anime/comments/1anfvtf/kekkon_yubiwa_monogatari_tales_of_wedding_rings/",
    "ups": 252,
    "upvote_ratio": 0.95,
    "view_count": null,
    "visited": false,
    "data_pull_date": {
      "timestamp": 1707715844.41289,
      "date": "2024-02-12 05:30:44"
    },
    "show_name": "Kekkon Yubiwa Monogatari \u2022 Tales of Wedding Rings",
    "season_number": 1,
    "episode_number": "6"
  },
  {
    "author": "AutoLovepon",
    "created_utc": 1707565928.0,
    "downs": 0,
    "discussion_type": null,
    "hide_score": false,
    "id": "1anenje",
    "num_comments": 1,
    "saved": false,
    "score": 2,
    "subreddit_id": "t5_2qh22",
    "title": "Meitantei Conan \u2022 Case Closed - Episode 1114 discussion",
    "total_awards_received": 0,
    "url": "https://www.reddit.com/r/anime/comments/1anenje/meitantei_conan_case_closed_episode_1114/",
    "ups": 2,
    "upvote_ratio": 0.6,
    "view_count": null,
    "visited": false,
    "data_pull_date": {
      "timestamp": 1707715844.41289,
      "date": "2024-02-12 05:30:44"
    },
    "show_name": "Meitantei Conan \u2022 Case Closed",
    "season_number": 1,
    "episode_number": "1114"
  },
  {
    "author": "AutoLovepon",
    "created_utc": 1707554421.0,
    "downs": 0,
    "discussion_type": null,
    "hide_score": false,
    "id": "1anbvut",
    "num_comments": 3,
    "saved": false,
    "score": 18,
    "subreddit_id": "t5_2qh22",
    "title": "Meitou \"Isekai no Yu\" Kaitaku-ki: Arafou Onsen Mania no Tensei Saki wa, Nonbiri Onsen Tengoku Deshita \u2022 Isekai Onsen Paradise - Episode 5 discussion",
    "total_awards_received": 0,
    "url": "https://www.reddit.com/r/anime/comments/1anbvut/meitou_isekai_no_yu_kaitakuki_arafou_onsen_mania/",
    "ups": 18,
    "upvote_ratio": 0.74,
    "view_count": null,
    "visited": false,
    "data_pull_date": {
      "timestamp": 1707715844.41289,
      "date": "2024-02-12 05:30:44"
    },
    "show_name": "Meitou \"Isekai no Yu\" Kaitaku-ki: Arafou Onsen Mania no Tensei Saki wa, Nonbiri Onsen Tengoku Deshita \u2022 Isekai Onsen Paradise",
    "season_number": 1,
    "episode_number": "5"
  },
  {
    "author": "AutoLovepon",
    "created_utc": 1707538224.0,
    "downs": 0,
    "discussion_type": null,
    "hide_score": false,
    "id": "1an7key",
    "num_comments": 19,
    "saved": false,
    "score": 52,
    "subreddit_id": "t5_2qh22",
    "title": "Pok\u00e9mon Horizons: The Series - Episode 39 discussion",
    "total_awards_received": 0,
    "url": "https://www.reddit.com/r/anime/comments/1an7key/pok\u00e9mon_horizons_the_series_episode_39_discussion/",
    "ups": 52,
    "upvote_ratio": 0.9,
    "view_count": null,
    "visited": false,
    "data_pull_date": {
      "timestamp": 1707715844.41289,
      "date": "2024-02-12 05:30:44"
    },
    "show_name": "Pok\u00e9mon Horizons: The Series",
    "season_number": 1,
    "episode_number": "39"
  },
  {
    "author": "AutoLovepon",
    "created_utc": 1707522639.0,
    "downs": 0,
    "discussion_type": null,
    "hide_score": false,
    "id": "1an2eda",
    "num_comments": 190,
    "saved": false,
    "score": 803,
    "subreddit_id": "t5_2qh22",
    "title": "Undead Unluck - Episode 18 discussion",
    "total_awards_received": 0,
    "url": "https://www.reddit.com/r/anime/comments/1an2eda/undead_unluck_episode_18_discussion/",
    "ups": 803,
    "upvote_ratio": 0.98,
    "view_count": null,
    "visited": false,
    "data_pull_date": {
      "timestamp": 1707715844.41289,
      "date": "2024-02-12 05:30:44"
    },
    "show_name": "Undead Unluck",
    "season_number": 1,
    "episode_number": "18"
  },
  {
    "author": "AutoLovepon",
    "created_utc": 1707522368.0,
    "downs": 0,
    "discussion_type": null,
    "hide_score": false,
    "id": "1an2aut",
    "num_comments": 17,
    "saved": false,
    "score": 54,
    "subreddit_id": "t5_2qh22",
    "title": "Pon no Michi \u2022 The Way of Pon - Episode 6 discussion",
    "total_awards_received": 0,
    "url": "https://www.reddit.com/r/anime/comments/1an2aut/pon_no_michi_the_way_of_pon_episode_6_discussion/",
    "ups": 54,
    "upvote_ratio": 0.87,
    "view_count": null,
    "visited": false,
    "data_pull_date": {
      "timestamp": 1707715844.41289,
      "date": "2024-02-12 05:30:44"
    },
    "show_name": "Pon no Michi \u2022 The Way of Pon",
    "season_number": 1,
    "episode_number": "6"
  },
  {
    "author": "AutoLovepon",
    "created_utc": 1707522194.0,
    "downs": 0,
    "discussion_type": null,
    "hide_score": false,
    "id": "1an28k0",
    "num_comments": 1,
    "saved": false,
    "score": 0,
    "subreddit_id": "t5_2qh22",
    "title": "CARDFIGHT!! VANGUARD Divinez - Episode 5 discussion",
    "total_awards_received": 0,
    "url": "https://www.reddit.com/r/anime/comments/1an28k0/cardfight_vanguard_divinez_episode_5_discussion/",
    "ups": 0,
    "upvote_ratio": 0.5,
    "view_count": null,
    "visited": false,
    "data_pull_date": {
      "timestamp": 1707715844.41289,
      "date": "2024-02-12 05:30:44"
    },
    "show_name": "CARDFIGHT!! VANGUARD Divinez",
    "season_number": 1,
    "episode_number": "5"
  },
  {
    "author": "AutoLovepon",
    "created_utc": 1707502753.0,
    "downs": 0,
    "discussion_type": null,
    "hide_score": false,
    "id": "1amurgz",
    "num_comments": 18,
    "saved": false,
    "score": 41,
    "subreddit_id": "t5_2qh22",
    "title": "Snack Basue - Episode 5 discussion",
    "total_awards_received": 0,
    "url": "https://www.reddit.com/r/anime/comments/1amurgz/snack_basue_episode_5_discussion/",
    "ups": 41,
    "upvote_ratio": 0.86,
    "view_count": null,
    "visited": false,
    "data_pull_date": {
      "timestamp": 1707715844.41289,
      "date": "2024-02-12 05:30:44"
    },
    "show_name": "Snack Basue",
    "season_number": 1,
    "episode_number": "5"
  },
  {
    "author": "AutoLovepon",
    "created_utc": 1707500253.0,
    "downs": 0,
    "discussion_type": null,
    "hide_score": false,
    "id": "1amtrip",
    "num_comments": 11,
    "saved": false,
    "score": 45,
    "subreddit_id": "t5_2qh22",
    "title": "Momochi-san Chi no Ayakashi Ouji \u2022 The Demon Prince of Momochi House - Episode 6 discussion",
    "total_awards_received": 0,
    "url": "https://www.reddit.com/r/anime/comments/1amtrip/momochisan_chi_no_ayakashi_ouji_the_demon_prince/",
    "ups": 45,
    "upvote_ratio": 0.82,
    "view_count": null,
    "visited": false,
    "data_pull_date": {
      "timestamp": 1707715844.41289,
      "date": "2024-02-12 05:30:44"
    },
    "show_name": "Momochi-san Chi no Ayakashi Ouji \u2022 The Demon Prince of Momochi House",
    "season_number": 1,
    "episode_number": "6"
  },
  {
    "author": "AutoLovepon",
    "created_utc": 1707494491.0,
    "downs": 0,
    "discussion_type": null,
    "hide_score": false,
    "id": "1amrfvc",
    "num_comments": 1022,
    "saved": false,
    "score": 5302,
    "subreddit_id": "t5_2qh22",
    "title": "Sousou no Frieren \u2022 Frieren: Beyond Journey's End - Episode 22 discussion",
    "total_awards_received": 0,
    "url": "https://www.reddit.com/r/anime/comments/1amrfvc/sousou_no_frieren_frieren_beyond_journeys_end/",
    "ups": 5302,
    "upvote_ratio": 0.95,
    "view_count": null,
    "visited": false,
    "data_pull_date": {
      "timestamp": 1707715844.41289,
      "date": "2024-02-12 05:30:44"
    },
    "show_name": "Sousou no Frieren \u2022 Frieren: Beyond Journey's End",
    "season_number": 1,
    "episode_number": "22"
  },
  {
    "author": "AutoLovepon",
    "created_utc": 1707493052.0,
    "downs": 0,
    "discussion_type": null,
    "hide_score": false,
    "id": "1amqvyz",
    "num_comments": 136,
    "saved": false,
    "score": 771,
    "subreddit_id": "t5_2qh22",
    "title": "Chiyu Mahou no Machigatta Tsukaikata: Senjou wo Kakeru Kaifuku Youin \u2022 The Wrong Way to Use Healing Magic - Episode 6 discussion",
    "total_awards_received": 0,
    "url": "https://www.reddit.com/r/anime/comments/1amqvyz/chiyu_mahou_no_machigatta_tsukaikata_senjou_wo/",
    "ups": 771,
    "upvote_ratio": 0.97,
    "view_count": null,
    "visited": false,
    "data_pull_date": {
      "timestamp": 1707715844.41289,
      "date": "2024-02-12 05:30:44"
    },
    "show_name": "Chiyu Mahou no Machigatta Tsukaikata: Senjou wo Kakeru Kaifuku Youin \u2022 The Wrong Way to Use Healing Magic",
    "season_number": 1,
    "episode_number": "6"
  },
  {
    "author": "AutoLovepon",
    "created_utc": 1707492678.0,
    "downs": 0,
    "discussion_type": null,
    "hide_score": false,
    "id": "1amqr0r",
    "num_comments": 222,
    "saved": false,
    "score": 447,
    "subreddit_id": "t5_2qh22",
    "title": "Saijaku Tamer wa Gomi Hiroi no Tabi wo Hajimemashita. \u2022 The Weakest Tamer Began a Journey to Pick Up Trash - Episode 5 discussion",
    "total_awards_received": 0,
    "url": "https://www.reddit.com/r/anime/comments/1amqr0r/saijaku_tamer_wa_gomi_hiroi_no_tabi_wo/",
    "ups": 447,
    "upvote_ratio": 0.96,
    "view_count": null,
    "visited": false,
    "data_pull_date": {
      "timestamp": 1707715844.41289,
      "date": "2024-02-12 05:30:44"
    },
    "show_name": "Saijaku Tamer wa Gomi Hiroi no Tabi wo Hajimemashita. \u2022 The Weakest Tamer Began a Journey to Pick Up Trash",
    "season_number": 1,
    "episode_number": "5"
  },
  {
    "author": "AutoLovepon",
    "created_utc": 1707489076.0,
    "downs": 0,
    "discussion_type": null,
    "hide_score": false,
    "id": "1ampfii",
    "num_comments": 151,
    "saved": false,
    "score": 533,
    "subreddit_id": "t5_2qh22",
    "title": "Nozomanu Fushi no Boukensha \u2022 The Unwanted Undead Adventurer - Episode 6 discussion",
    "total_awards_received": 0,
    "url": "https://www.reddit.com/r/anime/comments/1ampfii/nozomanu_fushi_no_boukensha_the_unwanted_undead/",
    "ups": 533,
    "upvote_ratio": 0.97,
    "view_count": null,
    "visited": false,
    "data_pull_date": {
      "timestamp": 1707715844.41289,
      "date": "2024-02-12 05:30:44"
    },
    "show_name": "Nozomanu Fushi no Boukensha \u2022 The Unwanted Undead Adventurer",
    "season_number": 1,
    "episode_number": "6"
  },
  {
    "author": "AutoLovepon",
    "created_utc": 1707485491.0,
    "downs": 0,
    "discussion_type": null,
    "hide_score": false,
    "id": "1amo7bn",
    "num_comments": 156,
    "saved": false,
    "score": 372,
    "subreddit_id": "t5_2qh22",
    "title": "Sasaki to Pii-chan \u2022 Sasaki and Peeps - Episode 6 discussion",
    "total_awards_received": 0,
    "url": "https://www.reddit.com/r/anime/comments/1amo7bn/sasaki_to_piichan_sasaki_and_peeps_episode_6/",
    "ups": 372,
    "upvote_ratio": 0.94,
    "view_count": null,
    "visited": false,
    "data_pull_date": {
      "timestamp": 1707715844.41289,
      "date": "2024-02-12 05:30:44"
    },
    "show_name": "Sasaki to Pii-chan \u2022 Sasaki and Peeps",
    "season_number": 1,
    "episode_number": "6"
  },
  {
    "author": "AutoLovepon",
    "created_utc": 1707476498.0,
    "downs": 0,
    "discussion_type": null,
    "hide_score": false,
    "id": "1amln5i",
    "num_comments": 5,
    "saved": false,
    "score": 13,
    "subreddit_id": "t5_2qh22",
    "title": "Odekake Kozame - Episode 34 discussion",
    "total_awards_received": 0,
    "url": "https://www.reddit.com/r/anime/comments/1amln5i/odekake_kozame_episode_34_discussion/",
    "ups": 13,
    "upvote_ratio": 0.79,
    "view_count": null,
    "visited": false,
    "data_pull_date": {
      "timestamp": 1707715844.41289,
      "date": "2024-02-12 05:30:44"
    },
    "show_name": "Odekake Kozame",
    "season_number": 1,
    "episode_number": "34"
  },
  {
    "author": "AutoLovepon",
    "created_utc": 1707430292.0,
    "downs": 0,
    "discussion_type": null,
    "hide_score": false,
    "id": "1am7t26",
    "num_comments": 33,
    "saved": false,
    "score": 217,
    "subreddit_id": "t5_2qh22",
    "title": "Urusei Yatsura (2022) Season 2 - Episode 5 discussion",
    "total_awards_received": 0,
    "url": "https://www.reddit.com/r/anime/comments/1am7t26/urusei_yatsura_2022_season_2_episode_5_discussion/",
    "ups": 217,
    "upvote_ratio": 0.93,
    "view_count": null,
    "visited": false,
    "data_pull_date": {
      "timestamp": 1707715844.41289,
      "date": "2024-02-12 05:30:44"
    },
    "show_name": "Urusei Yatsura (2022) Season 2",
    "season_number": "2",
    "episode_number": "5"
  },
  {
    "author": "AutoLovepon",
    "created_utc": 1707414342.0,
    "downs": 0,
    "discussion_type": null,
    "hide_score": false,
    "id": "1am1haa",
    "num_comments": 398,
    "saved": false,
    "score": 2331,
    "subreddit_id": "t5_2qh22",
    "title": "Dungeon Meshi \u2022 Delicious in Dungeon - Episode 6 discussion",
    "total_awards_received": 0,
    "url": "https://www.reddit.com/r/anime/comments/1am1haa/dungeon_meshi_delicious_in_dungeon_episode_6/",
    "ups": 2331,
    "upvote_ratio": 0.96,
    "view_count": null,
    "visited": false,
    "data_pull_date": {
      "timestamp": 1707715844.41289,
      "date": "2024-02-12 05:30:44"
    },
    "show_name": "Dungeon Meshi \u2022 Delicious in Dungeon",
    "season_number": 1,
    "episode_number": "6"
  },
  {
    "author": "AutoLovepon",
    "created_utc": 1707413645.0,
    "downs": 0,
    "discussion_type": null,
    "hide_score": false,
    "id": "1am17h9",
    "num_comments": 111,
    "saved": false,
    "score": 255,
    "subreddit_id": "t5_2qh22",
    "title": "Yuuki Bakuhatsu Bang Bravern \u2022 Brave Bang Bravern! - Episode 5 discussion",
    "total_awards_received": 0,
    "url": "https://www.reddit.com/r/anime/comments/1am17h9/yuuki_bakuhatsu_bang_bravern_brave_bang_bravern/",
    "ups": 255,
    "upvote_ratio": 0.94,
    "view_count": null,
    "visited": false,
    "data_pull_date": {
      "timestamp": 1707715844.41289,
      "date": "2024-02-12 05:30:44"
    },
    "show_name": "Yuuki Bakuhatsu Bang Bravern \u2022 Brave Bang Bravern!",
    "season_number": 1,
    "episode_number": "5"
  },
  {
    "author": "AutoLovepon",
    "created_utc": 1707413492.0,
    "downs": 0,
    "discussion_type": null,
    "hide_score": false,
    "id": "1am15cb",
    "num_comments": 139,
    "saved": false,
    "score": 473,
    "subreddit_id": "t5_2qh22",
    "title": "Majo to Yajuu \u2022 The Witch and the Beast - Episode 5 discussion",
    "total_awards_received": 0,
    "url": "https://www.reddit.com/r/anime/comments/1am15cb/majo_to_yajuu_the_witch_and_the_beast_episode_5/",
    "ups": 473,
    "upvote_ratio": 0.96,
    "view_count": null,
    "visited": false,
    "data_pull_date": {
      "timestamp": 1707715844.41289,
      "date": "2024-02-12 05:30:44"
    },
    "show_name": "Majo to Yajuu \u2022 The Witch and the Beast",
    "season_number": 1,
    "episode_number": "5"
  },
  {
    "author": "AutoLovepon",
    "created_utc": 1707409890.0,
    "downs": 0,
    "discussion_type": null,
    "hide_score": false,
    "id": "1alzp6d",
    "num_comments": 221,
    "saved": false,
    "score": 476,
    "subreddit_id": "t5_2qh22",
    "title": "Sokushi Cheat ga Saikyou Sugite, Isekai no Yatsura ga Marude Aite ni Naranaindesu ga. \u2022 My Instant Death Ability Is So Overpowered, No One in This Other World Stands a Chance Against Me! - Episode 6 discussion",
    "total_awards_received": 0,
    "url": "https://www.reddit.com/r/anime/comments/1alzp6d/sokushi_cheat_ga_saikyou_sugite_isekai_no_yatsura/",
    "ups": 476,
    "upvote_ratio": 0.94,
    "view_count": null,
    "visited": false,
    "data_pull_date": {
      "timestamp": 1707715844.41289,
      "date": "2024-02-12 05:30:44"
    },
    "show_name": "Sokushi Cheat ga Saikyou Sugite, Isekai no Yatsura ga Marude Aite ni Naranaindesu ga. \u2022 My Instant Death Ability Is So Overpowered, No One in This Other World Stands a Chance Against Me!",
    "season_number": 1,
    "episode_number": "6"
  },
  {
    "author": "AutoLovepon",
    "created_utc": 1707409878.0,
    "downs": 0,
    "discussion_type": null,
    "hide_score": false,
    "id": "1alzp0l",
    "num_comments": 4,
    "saved": false,
    "score": 11,
    "subreddit_id": "t5_2qh22",
    "title": "Gekkan Mousou Kagaku \u2022 Delusional Monthly Magazine - Episode 5 discussion",
    "total_awards_received": 0,
    "url": "https://www.reddit.com/r/anime/comments/1alzp0l/gekkan_mousou_kagaku_delusional_monthly_magazine/",
    "ups": 11,
    "upvote_ratio": 0.72,
    "view_count": null,
    "visited": false,
    "data_pull_date": {
      "timestamp": 1707715844.41289,
      "date": "2024-02-12 05:30:44"
    },
    "show_name": "Gekkan Mousou Kagaku \u2022 Delusional Monthly Magazine",
    "season_number": 1,
    "episode_number": "5"
  },
  {
    "author": "AutoLovepon",
    "created_utc": 1707404488.0,
    "downs": 0,
    "discussion_type": null,
    "hide_score": false,
    "id": "1alxnkw",
    "num_comments": 196,
    "saved": false,
    "score": 686,
    "subreddit_id": "t5_2qh22",
    "title": "Mato Seihei no Slave \u2022 Chained Soldier - Episode 6 discussion",
    "total_awards_received": 0,
    "url": "https://www.reddit.com/r/anime/comments/1alxnkw/mato_seihei_no_slave_chained_soldier_episode_6/",
    "ups": 686,
    "upvote_ratio": 0.93,
    "view_count": null,
    "visited": false,
    "data_pull_date": {
      "timestamp": 1707715844.41289,
      "date": "2024-02-12 05:30:44"
    },
    "show_name": "Mato Seihei no Slave \u2022 Chained Soldier",
    "season_number": 1,
    "episode_number": "6"
  },
  {
    "author": "AutoLovepon",
    "created_utc": 1707358415.0,
    "downs": 0,
    "discussion_type": null,
    "hide_score": false,
    "id": "1alkmhr",
    "num_comments": 2,
    "saved": false,
    "score": 8,
    "subreddit_id": "t5_2qh22",
    "title": "Beyblade X - Episode 17 discussion",
    "total_awards_received": 0,
    "url": "https://www.reddit.com/r/anime/comments/1alkmhr/beyblade_x_episode_17_discussion/",
    "ups": 8,
    "upvote_ratio": 0.71,
    "view_count": null,
    "visited": false,
    "data_pull_date": {
      "timestamp": 1707715844.41289,
      "date": "2024-02-12 05:30:44"
    },
    "show_name": "Beyblade X",
    "season_number": 1,
    "episode_number": "17"
  },
  {
    "author": "AutoLovepon",
    "created_utc": 1707327092.0,
    "downs": 0,
    "discussion_type": null,
    "hide_score": false,
    "id": "1al8gxg",
    "num_comments": 56,
    "saved": false,
    "score": 134,
    "subreddit_id": "t5_2qh22",
    "title": "30-sai made Doutei dato Mahoutsukai ni Nareru Rashii \u2022 Cherry Magic! Thirty Years of Virginity Can Make You a Wizard?! - Episode 5 discussion",
    "total_awards_received": 0,
    "url": "https://www.reddit.com/r/anime/comments/1al8gxg/30sai_made_doutei_dato_mahoutsukai_ni_nareru/",
    "ups": 134,
    "upvote_ratio": 0.9,
    "view_count": null,
    "visited": false,
    "data_pull_date": {
      "timestamp": 1707715844.41289,
      "date": "2024-02-12 05:30:44"
    },
    "show_name": "30-sai made Doutei dato Mahoutsukai ni Nareru Rashii \u2022 Cherry Magic! Thirty Years of Virginity Can Make You a Wizard?!",
    "season_number": 1,
    "episode_number": "5"
  },
  {
    "author": "AutoLovepon",
    "created_utc": 1707325654.0,
    "downs": 0,
    "discussion_type": null,
    "hide_score": false,
    "id": "1al7vgi",
    "num_comments": 1,
    "saved": false,
    "score": 3,
    "subreddit_id": "t5_2qh22",
    "title": "Chou Futsuu-ken Chiba Densetsu \u2022 The Legend of Super Normal Pref. Chiba - Episode 5 discussion",
    "total_awards_received": 0,
    "url": "https://www.reddit.com/r/anime/comments/1al7vgi/chou_futsuuken_chiba_densetsu_the_legend_of_super/",
    "ups": 3,
    "upvote_ratio": 0.67,
    "view_count": null,
    "visited": false,
    "data_pull_date": {
      "timestamp": 1707715844.41289,
      "date": "2024-02-12 05:30:44"
    },
    "show_name": "Chou Futsuu-ken Chiba Densetsu \u2022 The Legend of Super Normal Pref. Chiba",
    "season_number": 1,
    "episode_number": "5"
  },
  {
    "author": "AutoLovepon",
    "created_utc": 1707325292.0,
    "downs": 0,
    "discussion_type": null,
    "hide_score": false,
    "id": "1al7q28",
    "num_comments": 160,
    "saved": false,
    "score": 663,
    "subreddit_id": "t5_2qh22",
    "title": "Metallic Rouge - Episode 5 discussion",
    "total_awards_received": 0,
    "url": "https://www.reddit.com/r/anime/comments/1al7q28/metallic_rouge_episode_5_discussion/",
    "ups": 663,
    "upvote_ratio": 0.97,
    "view_count": null,
    "visited": false,
    "data_pull_date": {
      "timestamp": 1707715844.41289,
      "date": "2024-02-12 05:30:44"
    },
    "show_name": "Metallic Rouge",
    "season_number": 1,
    "episode_number": "5"
  },
  {
    "author": "AutoLovepon",
    "created_utc": 1707323477.0,
    "downs": 0,
    "discussion_type": null,
    "hide_score": false,
    "id": "1al6zok",
    "num_comments": 82,
    "saved": false,
    "score": 402,
    "subreddit_id": "t5_2qh22",
    "title": "Sengoku Youko - Episode 5 discussion",
    "total_awards_received": 0,
    "url": "https://www.reddit.com/r/anime/comments/1al6zok/sengoku_youko_episode_5_discussion/",
    "ups": 402,
    "upvote_ratio": 0.97,
    "view_count": null,
    "visited": false,
    "data_pull_date": {
      "timestamp": 1707715844.41289,
      "date": "2024-02-12 05:30:44"
    },
    "show_name": "Sengoku Youko",
    "season_number": 1,
    "episode_number": "5"
  },
  {
    "author": "AutoLovepon",
    "created_utc": 1707321689.0,
    "downs": 0,
    "discussion_type": null,
    "hide_score": false,
    "id": "1al69m7",
    "num_comments": 404,
    "saved": false,
    "score": 1711,
    "subreddit_id": "t5_2qh22",
    "title": "Mahou Shoujo ni Akogarete \u2022 Gushing over Magical Girls - Episode 6 discussion",
    "total_awards_received": 0,
    "url": "https://www.reddit.com/r/anime/comments/1al69m7/mahou_shoujo_ni_akogarete_gushing_over_magical/",
    "ups": 1711,
    "upvote_ratio": 0.95,
    "view_count": null,
    "visited": false,
    "data_pull_date": {
      "timestamp": 1707715844.41289,
      "date": "2024-02-12 05:30:44"
    },
    "show_name": "Mahou Shoujo ni Akogarete \u2022 Gushing over Magical Girls",
    "season_number": 1,
    "episode_number": "6"
  },
  {
    "author": "AutoLovepon",
    "created_utc": 1707318095.0,
    "downs": 0,
    "discussion_type": null,
    "hide_score": false,
    "id": "1al4wkw",
    "num_comments": 106,
    "saved": false,
    "score": 264,
    "subreddit_id": "t5_2qh22",
    "title": "Ishura - Episode 6 discussion",
    "total_awards_received": 0,
    "url": "https://www.reddit.com/r/anime/comments/1al4wkw/ishura_episode_6_discussion/",
    "ups": 264,
    "upvote_ratio": 0.95,
    "view_count": null,
    "visited": false,
    "data_pull_date": {
      "timestamp": 1707715844.41289,
      "date": "2024-02-12 05:30:44"
    },
    "show_name": "Ishura",
    "season_number": 1,
    "episode_number": "6"
  },
  {
    "author": "AutoLovepon",
    "created_utc": 1707316279.0,
    "downs": 0,
    "discussion_type": null,
    "hide_score": false,
    "id": "1al48du",
    "num_comments": 90,
    "saved": false,
    "score": 204,
    "subreddit_id": "t5_2qh22",
    "title": "Gekai Elise \u2022 Doctor Elise: The Royal Lady with the Lamp - Episode 5 discussion",
    "total_awards_received": 0,
    "url": "https://www.reddit.com/r/anime/comments/1al48du/gekai_elise_doctor_elise_the_royal_lady_with_the/",
    "ups": 204,
    "upvote_ratio": 0.92,
    "view_count": null,
    "visited": false,
    "data_pull_date": {
      "timestamp": 1707715844.41289,
      "date": "2024-02-12 05:30:44"
    },
    "show_name": "Gekai Elise \u2022 Doctor Elise: The Royal Lady with the Lamp",
    "season_number": 1,
    "episode_number": "5"
  },
  {
    "author": "AutoLovepon",
    "created_utc": 1707313039.0,
    "downs": 0,
    "discussion_type": null,
    "hide_score": false,
    "id": "1al337s",
    "num_comments": 218,
    "saved": false,
    "score": 840,
    "subreddit_id": "t5_2qh22",
    "title": "Youkoso Jitsuryoku Shijou Shugi no Kyoushitsu e Season 3 \u2022 Classroom of the Elite Season 3 - Episode 6 discussion",
    "total_awards_received": 0,
    "url": "https://www.reddit.com/r/anime/comments/1al337s/youkoso_jitsuryoku_shijou_shugi_no_kyoushitsu_e/",
    "ups": 840,
    "upvote_ratio": 0.94,
    "view_count": null,
    "visited": false,
    "data_pull_date": {
      "timestamp": 1707715844.41289,
      "date": "2024-02-12 05:30:44"
    },
    "show_name": "Youkoso Jitsuryoku Shijou Shugi no Kyoushitsu e Season 3 \u2022 Classroom of the Elite Season 3",
    "season_number": "3",
    "episode_number": "6"
  },
  {
    "author": "AutoLovepon",
    "created_utc": 1707312677.0,
    "downs": 0,
    "discussion_type": null,
    "hide_score": false,
    "id": "1al2yzi",
    "num_comments": 185,
    "saved": false,
    "score": 472,
    "subreddit_id": "t5_2qh22",
    "title": "Jaku-Chara Tomozaki-kun 2nd Stage \u2022 Bottom-tier Character Tomozaki 2nd Stage - Episode 6 discussion",
    "total_awards_received": 0,
    "url": "https://www.reddit.com/r/anime/comments/1al2yzi/jakuchara_tomozakikun_2nd_stage_bottomtier/",
    "ups": 472,
    "upvote_ratio": 0.96,
    "view_count": null,
    "visited": false,
    "data_pull_date": {
      "timestamp": 1707715844.41289,
      "date": "2024-02-12 05:30:44"
    },
    "show_name": "Jaku-Chara Tomozaki-kun 2nd Stage \u2022 Bottom-tier Character Tomozaki 2nd Stage",
    "season_number": 1,
    "episode_number": "6"
  },
  {
    "author": "AutoLovepon",
    "created_utc": 1707277051.0,
    "downs": 0,
    "discussion_type": null,
    "hide_score": false,
    "id": "1akth8g",
    "num_comments": 5,
    "saved": false,
    "score": 12,
    "subreddit_id": "t5_2qh22",
    "title": "Dog Signal - Episode 14 discussion",
    "total_awards_received": 0,
    "url": "https://www.reddit.com/r/anime/comments/1akth8g/dog_signal_episode_14_discussion/",
    "ups": 12,
    "upvote_ratio": 0.83,
    "view_count": null,
    "visited": false,
    "data_pull_date": {
      "timestamp": 1707715844.41289,
      "date": "2024-02-12 05:30:44"
    },
    "show_name": "Dog Signal",
    "season_number": 1,
    "episode_number": "14"
  },
  {
    "author": "AutoLovepon",
    "created_utc": 1707241772.0,
    "downs": 0,
    "discussion_type": null,
    "hide_score": false,
    "id": "1akfqnp",
    "num_comments": 386,
    "saved": false,
    "score": 1217,
    "subreddit_id": "t5_2qh22",
    "title": "Akuyaku Reijou Level 99: Watashi wa Ura-Boss desu ga Maou dewa Arimasen \u2022 Villainess Level 99: I May Be the Hidden Boss but I'm Not the Demon Lord - Episode 5 discussion",
    "total_awards_received": 0,
    "url": "https://www.reddit.com/r/anime/comments/1akfqnp/akuyaku_reijou_level_99_watashi_wa_uraboss_desu/",
    "ups": 1217,
    "upvote_ratio": 0.95,
    "view_count": null,
    "visited": false,
    "data_pull_date": {
      "timestamp": 1707715844.41289,
      "date": "2024-02-12 05:30:44"
    },
    "show_name": "Akuyaku Reijou Level 99: Watashi wa Ura-Boss desu ga Maou dewa Arimasen \u2022 Villainess Level 99: I May Be the Hidden Boss but I'm Not the Demon Lord",
    "season_number": 1,
    "episode_number": "5"
  },
  {
    "author": "AutoLovepon",
    "created_utc": 1707217297.0,
    "downs": 0,
    "discussion_type": null,
    "hide_score": false,
    "id": "1ak775l",
    "num_comments": 7,
    "saved": false,
    "score": 20,
    "subreddit_id": "t5_2qh22",
    "title": "Odekake Kozame - Episode 33 discussion",
    "total_awards_received": 0,
    "url": "https://www.reddit.com/r/anime/comments/1ak775l/odekake_kozame_episode_33_discussion/",
    "ups": 20,
    "upvote_ratio": 0.91,
    "view_count": null,
    "visited": false,
    "data_pull_date": {
      "timestamp": 1707715844.41289,
      "date": "2024-02-12 05:30:44"
    },
    "show_name": "Odekake Kozame",
    "season_number": 1,
    "episode_number": "33"
  },
  {
    "author": "AutoLovepon",
    "created_utc": 1707156438.0,
    "downs": 0,
    "discussion_type": null,
    "hide_score": false,
    "id": "1ajn41r",
    "num_comments": 67,
    "saved": false,
    "score": 168,
    "subreddit_id": "t5_2qh22",
    "title": "Buta no Liver wa Kanetsu Shiro \u2022 Butareba -The Story of a Man Turned into a Pig- - Episode 12 discussion - FINAL",
    "total_awards_received": 0,
    "url": "https://www.reddit.com/r/anime/comments/1ajn41r/buta_no_liver_wa_kanetsu_shiro_butareba_the_story/",
    "ups": 168,
    "upvote_ratio": 0.88,
    "view_count": null,
    "visited": false,
    "data_pull_date": {
      "timestamp": 1707715844.41289,
      "date": "2024-02-12 05:30:44"
    },
    "show_name": "Buta no Liver wa Kanetsu Shiro \u2022 Butareba -The Story of a Man Turned into a Pig-",
    "season_number": 1,
    "episode_number": "12"
  },
  {
    "author": "AutoLovepon",
    "created_utc": 1707155546.0,
    "downs": 0,
    "discussion_type": null,
    "hide_score": false,
    "id": "1ajmq0o",
    "num_comments": 137,
    "saved": false,
    "score": 413,
    "subreddit_id": "t5_2qh22",
    "title": "Dosanko Gal wa Namara Menkoi \u2022 Hokkaido Gals Are Super Adorable! - Episode 5 discussion",
    "total_awards_received": 0,
    "url": "https://www.reddit.com/r/anime/comments/1ajmq0o/dosanko_gal_wa_namara_menkoi_hokkaido_gals_are/",
    "ups": 413,
    "upvote_ratio": 0.93,
    "view_count": null,
    "visited": false,
    "data_pull_date": {
      "timestamp": 1707715844.41289,
      "date": "2024-02-12 05:30:44"
    },
    "show_name": "Dosanko Gal wa Namara Menkoi \u2022 Hokkaido Gals Are Super Adorable!",
    "season_number": 1,
    "episode_number": "5"
  },
  {
    "author": "AutoLovepon",
    "created_utc": 1707154280.0,
    "downs": 0,
    "discussion_type": null,
    "hide_score": false,
    "id": "1ajm6av",
    "num_comments": 99,
    "saved": false,
    "score": 401,
    "subreddit_id": "t5_2qh22",
    "title": "Hime-sama \"Goumon\" no Jikan desu \u2022 'Tis Time for \"Torture,\" Princess - Episode 5 discussion",
    "total_awards_received": 0,
    "url": "https://www.reddit.com/r/anime/comments/1ajm6av/himesama_goumon_no_jikan_desu_tis_time_for/",
    "ups": 401,
    "upvote_ratio": 0.94,
    "view_count": null,
    "visited": false,
    "data_pull_date": {
      "timestamp": 1707715844.41289,
      "date": "2024-02-12 05:30:44"
    },
    "show_name": "Hime-sama \"Goumon\" no Jikan desu \u2022 'Tis Time for \"Torture,\" Princess",
    "season_number": 1,
    "episode_number": "5"
  },
  {
    "author": "AutoLovepon",
    "created_utc": 1707151057.0,
    "downs": 0,
    "discussion_type": null,
    "hide_score": false,
    "id": "1ajksoc",
    "num_comments": 78,
    "saved": false,
    "score": 329,
    "subreddit_id": "t5_2qh22",
    "title": "Oroka na Tenshi wa Akuma to Odoru \u2022 The Foolish Angel Dances with the Devil - Episode 5 discussion",
    "total_awards_received": 0,
    "url": "https://www.reddit.com/r/anime/comments/1ajksoc/oroka_na_tenshi_wa_akuma_to_odoru_the_foolish/",
    "ups": 329,
    "upvote_ratio": 0.94,
    "view_count": null,
    "visited": false,
    "data_pull_date": {
      "timestamp": 1707715844.41289,
      "date": "2024-02-12 05:30:44"
    },
    "show_name": "Oroka na Tenshi wa Akuma to Odoru \u2022 The Foolish Angel Dances with the Devil",
    "season_number": 1,
    "episode_number": "5"
  },
  {
    "author": "AutoLovepon",
    "created_utc": 1707150338.0,
    "downs": 0,
    "discussion_type": null,
    "hide_score": false,
    "id": "1ajki72",
    "num_comments": 68,
    "saved": false,
    "score": 96,
    "subreddit_id": "t5_2qh22",
    "title": "Synduality Noir Part 2 - Episode 5 discussion",
    "total_awards_received": 0,
    "url": "https://www.reddit.com/r/anime/comments/1ajki72/synduality_noir_part_2_episode_5_discussion/",
    "ups": 96,
    "upvote_ratio": 0.91,
    "view_count": null,
    "visited": false,
    "data_pull_date": {
      "timestamp": 1707715844.41289,
      "date": "2024-02-12 05:30:44"
    },
    "show_name": "Synduality Noir Part 2",
    "season_number": 1,
    "episode_number": "5"
  },
  {
    "author": "AutoLovepon",
    "created_utc": 1707145657.0,
    "downs": 0,
    "discussion_type": null,
    "hide_score": false,
    "id": "1ajioh1",
    "num_comments": 204,
    "saved": false,
    "score": 755,
    "subreddit_id": "t5_2qh22",
    "title": "Tsuki ga Michibiku Isekai Douchuu Season 2 \u2022 Tsukimichi -Moonlit Fantasy- Season 2 - Episode 5 discussion",
    "total_awards_received": 0,
    "url": "https://www.reddit.com/r/anime/comments/1ajioh1/tsuki_ga_michibiku_isekai_douchuu_season_2/",
    "ups": 755,
    "upvote_ratio": 0.97,
    "view_count": null,
    "visited": false,
    "data_pull_date": {
      "timestamp": 1707715844.41289,
      "date": "2024-02-12 05:30:44"
    },
    "show_name": "Tsuki ga Michibiku Isekai Douchuu Season 2 \u2022 Tsukimichi -Moonlit Fantasy- Season 2",
    "season_number": "2",
    "episode_number": "5"
  },
  {
    "author": "AutoLovepon",
    "created_utc": 1707139879.0,
    "downs": 0,
    "discussion_type": null,
    "hide_score": false,
    "id": "1ajgk79",
    "num_comments": 48,
    "saved": false,
    "score": 80,
    "subreddit_id": "t5_2qh22",
    "title": "High Card Season 2 - Episode 17 discussion",
    "total_awards_received": 0,
    "url": "https://www.reddit.com/r/anime/comments/1ajgk79/high_card_season_2_episode_17_discussion/",
    "ups": 80,
    "upvote_ratio": 0.88,
    "view_count": null,
    "visited": false,
    "data_pull_date": {
      "timestamp": 1707715844.41289,
      "date": "2024-02-12 05:30:44"
    },
    "show_name": "High Card Season 2",
    "season_number": "2",
    "episode_number": "17"
  },
  {
    "author": "AutoLovepon",
    "created_utc": 1707130174.0,
    "downs": 0,
    "discussion_type": null,
    "hide_score": false,
    "id": "1ajdq65",
    "num_comments": 4,
    "saved": false,
    "score": 10,
    "subreddit_id": "t5_2qh22",
    "title": "Nanatsu no Taizai: Mokushiroku no Yonkishi \u2022 The Seven Deadly Sins: Four Knights of the Apocalypse - Episode 16 discussion",
    "total_awards_received": 0,
    "url": "https://www.reddit.com/r/anime/comments/1ajdq65/nanatsu_no_taizai_mokushiroku_no_yonkishi_the/",
    "ups": 10,
    "upvote_ratio": 0.7,
    "view_count": null,
    "visited": false,
    "data_pull_date": {
      "timestamp": 1707715844.41289,
      "date": "2024-02-12 05:30:44"
    },
    "show_name": "Nanatsu no Taizai: Mokushiroku no Yonkishi \u2022 The Seven Deadly Sins: Four Knights of the Apocalypse",
    "season_number": 1,
    "episode_number": "16"
  },
  {
    "author": "AutoLovepon",
    "created_utc": 1707079771.0,
    "downs": 0,
    "discussion_type": null,
    "hide_score": false,
    "id": "1aiy59k",
    "num_comments": 1,
    "saved": false,
    "score": 7,
    "subreddit_id": "t5_2qh22",
    "title": "Yami Shibai 12 \u2022 Theatre of Darkness: Yamishibai 12 - Episode 4 discussion",
    "total_awards_received": 0,
    "url": "https://www.reddit.com/r/anime/comments/1aiy59k/yami_shibai_12_theatre_of_darkness_yamishibai_12/",
    "ups": 7,
    "upvote_ratio": 0.89,
    "view_count": null,
    "visited": false,
    "data_pull_date": {
      "timestamp": 1707715844.41289,
      "date": "2024-02-12 05:30:44"
    },
    "show_name": "Yami Shibai 12 \u2022 Theatre of Darkness: Yamishibai 12",
    "season_number": 1,
    "episode_number": "4"
  },
  {
    "author": "AutoLovepon",
    "created_utc": 1707072555.0,
    "downs": 0,
    "discussion_type": null,
    "hide_score": false,
    "id": "1aiv6km",
    "num_comments": 59,
    "saved": false,
    "score": 176,
    "subreddit_id": "t5_2qh22",
    "title": "Kyuujitsu no Warumono-san \u2022 Mr. Villain's Day Off - Episode 5 discussion",
    "total_awards_received": 0,
    "url": "https://www.reddit.com/r/anime/comments/1aiv6km/kyuujitsu_no_warumonosan_mr_villains_day_off/",
    "ups": 176,
    "upvote_ratio": 0.94,
    "view_count": null,
    "visited": false,
    "data_pull_date": {
      "timestamp": 1707715844.41289,
      "date": "2024-02-12 05:30:44"
    },
    "show_name": "Kyuujitsu no Warumono-san \u2022 Mr. Villain's Day Off",
    "season_number": 1,
    "episode_number": "5"
  },
  {
    "author": "AutoLovepon",
    "created_utc": 1707064276.0,
    "downs": 0,
    "discussion_type": null,
    "hide_score": false,
    "id": "1airup2",
    "num_comments": 26,
    "saved": false,
    "score": 121,
    "subreddit_id": "t5_2qh22",
    "title": "Hikari no Ou Season 2 \u2022 The Fire Hunter Season 2 - Episode 14 discussion",
    "total_awards_received": 0,
    "url": "https://www.reddit.com/r/anime/comments/1airup2/hikari_no_ou_season_2_the_fire_hunter_season_2/",
    "ups": 121,
    "upvote_ratio": 0.9,
    "view_count": null,
    "visited": false,
    "data_pull_date": {
      "timestamp": 1707715844.41289,
      "date": "2024-02-12 05:30:44"
    },
    "show_name": "Hikari no Ou Season 2 \u2022 The Fire Hunter Season 2",
    "season_number": "2",
    "episode_number": "14"
  },
  {
    "author": "AutoLovepon",
    "created_utc": 1707063173.0,
    "downs": 0,
    "discussion_type": null,
    "hide_score": false,
    "id": "1airf0r",
    "num_comments": 317,
    "saved": false,
    "score": 912,
    "subreddit_id": "t5_2qh22",
    "title": "Loop 7-kaime no Akuyaku Reijou wa, Moto Tekikoku de Jiyuu Kimama na Hanayome Seikatsu wo Mankitsu suru \u2022 7th Time Loop: The Villainess Enjoys a Carefree Life Married to Her Worst Enemy! - Episode 5 discussion",
    "total_awards_received": 0,
    "url": "https://www.reddit.com/r/anime/comments/1airf0r/loop_7kaime_no_akuyaku_reijou_wa_moto_tekikoku_de/",
    "ups": 912,
    "upvote_ratio": 0.98,
    "view_count": null,
    "visited": false,
    "data_pull_date": {
      "timestamp": 1707715844.41289,
      "date": "2024-02-12 05:30:44"
    },
    "show_name": "Loop 7-kaime no Akuyaku Reijou wa, Moto Tekikoku de Jiyuu Kimama na Hanayome Seikatsu wo Mankitsu suru \u2022 7th Time Loop: The Villainess Enjoys a Carefree Life Married to Her Worst Enemy!",
    "season_number": 1,
    "episode_number": "5"
  },
  {
    "author": "AutoLovepon",
    "created_utc": 1707062491.0,
    "downs": 0,
    "discussion_type": null,
    "hide_score": false,
    "id": "1air566",
    "num_comments": 23,
    "saved": false,
    "score": 60,
    "subreddit_id": "t5_2qh22",
    "title": "Meiji Gekken: 1874 - Episode 4 discussion",
    "total_awards_received": 0,
    "url": "https://www.reddit.com/r/anime/comments/1air566/meiji_gekken_1874_episode_4_discussion/",
    "ups": 60,
    "upvote_ratio": 0.91,
    "view_count": null,
    "visited": false,
    "data_pull_date": {
      "timestamp": 1707715844.41289,
      "date": "2024-02-12 05:30:44"
    },
    "show_name": "Meiji Gekken: 1874",
    "season_number": 1,
    "episode_number": "4"
  },
  {
    "author": "AutoLovepon",
    "created_utc": 1707060676.0,
    "downs": 0,
    "discussion_type": null,
    "hide_score": false,
    "id": "1aiqg69",
    "num_comments": 104,
    "saved": false,
    "score": 370,
    "subreddit_id": "t5_2qh22",
    "title": "Shin no Nakama ja Nai to Yuusha no Party wo Oidasareta node, Henkyou de Slow Life suru Koto ni Shimashita Season 2 \u2022 Banished from the Hero's Party, I Decided to Live a Quiet Life in the Countryside Season 2 - Episode 5 discussion",
    "total_awards_received": 0,
    "url": "https://www.reddit.com/r/anime/comments/1aiqg69/shin_no_nakama_ja_nai_to_yuusha_no_party_wo/",
    "ups": 370,
    "upvote_ratio": 0.94,
    "view_count": null,
    "visited": false,
    "data_pull_date": {
      "timestamp": 1707715844.41289,
      "date": "2024-02-12 05:30:44"
    },
    "show_name": "Shin no Nakama ja Nai to Yuusha no Party wo Oidasareta node, Henkyou de Slow Life suru Koto ni Shimashita Season 2 \u2022 Banished from the Hero's Party, I Decided to Live a Quiet Life in the Countryside Season 2",
    "season_number": "2",
    "episode_number": "5"
  },
  {
    "author": "AutoLovepon",
    "created_utc": 1707058879.0,
    "downs": 0,
    "discussion_type": null,
    "hide_score": false,
    "id": "1aiprsw",
    "num_comments": 136,
    "saved": false,
    "score": 211,
    "subreddit_id": "t5_2qh22",
    "title": "Isekai de Mofumofu Nadenade suru Tame ni Ganbattemasu. \u2022 Fluffy Paradise - Episode 6 discussion",
    "total_awards_received": 0,
    "url": "https://www.reddit.com/r/anime/comments/1aiprsw/isekai_de_mofumofu_nadenade_suru_tame_ni/",
    "ups": 211,
    "upvote_ratio": 0.93,
    "view_count": null,
    "visited": false,
    "data_pull_date": {
      "timestamp": 1707715844.41289,
      "date": "2024-02-12 05:30:44"
    },
    "show_name": "Isekai de Mofumofu Nadenade suru Tame ni Ganbattemasu. \u2022 Fluffy Paradise",
    "season_number": 1,
    "episode_number": "6"
  },
  {
    "author": "AutoLovepon",
    "created_utc": 1707054212.0,
    "downs": 0,
    "discussion_type": null,
    "hide_score": false,
    "id": "1aio6kd",
    "num_comments": 5,
    "saved": false,
    "score": 43,
    "subreddit_id": "t5_2qh22",
    "title": "Meitou \"Isekai no Yu\" Kaitaku-ki: Arafou Onsen Mania no Tensei Saki wa, Nonbiri Onsen Tengoku Deshita \u2022 Isekai Onsen Paradise - Episode 4 discussion",
    "total_awards_received": 0,
    "url": "https://www.reddit.com/r/anime/comments/1aio6kd/meitou_isekai_no_yu_kaitakuki_arafou_onsen_mania/",
    "ups": 43,
    "upvote_ratio": 0.82,
    "view_count": null,
    "visited": false,
    "data_pull_date": {
      "timestamp": 1707715844.41289,
      "date": "2024-02-12 05:30:44"
    },
    "show_name": "Meitou \"Isekai no Yu\" Kaitaku-ki: Arafou Onsen Mania no Tensei Saki wa, Nonbiri Onsen Tengoku Deshita \u2022 Isekai Onsen Paradise",
    "season_number": 1,
    "episode_number": "4"
  }
]